fw_gear_monai_transforms/__init__.py
fw_gear_monai_transforms/parser.py
fw_gear_monai_transforms/transform.py
fw_gear_monai_transforms/utils.py
fw_gear_monai_transforms-0.1.1.dist-info/METADATA
fw_gear_monai_transforms-0.1.1.dist-info/WHEEL
fw_gear_monai_transforms-0.1.1.dist-info/licenses/LICENSE
fw_gear_monai_transforms-0.1.1.dist-info/RECORD
