Metadata-Version: 2.4
Name: fw-gear-monai-transforms
Version: 0.1.1
Summary: Apply the MONAI tranforms as specified by the user input script and save output in the destination container
Project-URL: Repository, https://gitlab.com/flywheel-io/scientific-solutions/gears/monai-transforms
Author-email: Flywheel <support@flywheel.io>
License-Expression: MIT
License-File: LICENSE
Keywords: Flywheel,Gears
Classifier: Topic :: Scientific/Engineering
Requires-Python: <4,>=3.11
Requires-Dist: flywheel-gear-toolkit<0.7,>=0.6
Requires-Dist: fw-utils<6,>=5.1.0
Requires-Dist: monai[ignite,imagecodecs,itk,matplotlib,nibabel,pandas,pillow,skimage,tifffile,torchvision,transformers]<2,>=1.5.1
